meetingscribe/__init__.py
meetingscribe/audio.py
meetingscribe/chat.py
meetingscribe/main.py
meetingscribe/misc.py
meetingscribe/text.py
meetingscribe-0.1.2.dist-info/entry_points.txt
meetingscribe-0.1.2.dist-info/LICENSE
meetingscribe-0.1.2.dist-info/WHEEL
meetingscribe-0.1.2.dist-info/METADATA
meetingscribe-0.1.2.dist-info/RECORD
