Metadata-Version: 2.1
Name: meetingscribe
Version: 0.1.2
Summary: MeetingScribe is an AI-driven command-line tool designed to streamline your meeting experience by handling transcription, translation, and note-taking. Effortlessly generate accurate translation/transcription in English from audio file. Additionally, the tool intelligently creates meeting notes, summaries, and identifies action items.
Home-page: https://github.com/0x77dev/meetingscribe
License: MIT
Author: Mykhailo Marynenko
Author-email: mykhailo@0x77.dev
Requires-Python: >=3.9,<4.0
Classifier: License :: OSI Approved :: MIT License
Classifier: Programming Language :: Python :: 3
Classifier: Programming Language :: Python :: 3.10
Classifier: Programming Language :: Python :: 3.9
Requires-Dist: aiohttp[all] (>=3.8.4,<4.0.0)
Requires-Dist: cchardet[all] (>=2.1.7,<3.0.0)
Requires-Dist: openai[all] (>=0.27.2,<0.28.0)
Requires-Dist: pydub[all] (>=0.25.1,<0.26.0)
Requires-Dist: pysrt[all] (>=1.1.2,<2.0.0)
Requires-Dist: rich (==10.11.0)
Requires-Dist: srt[all] (>=3.5.2,<4.0.0)
Requires-Dist: typer[all] (>=0.7.0,<0.8.0)
